setup.py
src/cfnupdateservice/__init__.py
src/cfnupdateservice/logging.py
src/cfnupdateservice/tests.py
src/cfnupdateservice.egg-info/PKG-INFO
src/cfnupdateservice.egg-info/SOURCES.txt
src/cfnupdateservice.egg-info/dependency_links.txt
src/cfnupdateservice.egg-info/entry_points.txt
src/cfnupdateservice.egg-info/requires.txt
src/cfnupdateservice.egg-info/top_level.txt