Metadata-Version: 1.0
Name: cfnupdateservice
Version: 1.0.0
Summary: UNKNOWN
Home-page: https://github.com/hautelook/cfn-update-service
Author: Naftuli Tzvi Kay
Author-email: rfkrocktk@gmail.com
License: UNKNOWN
Platform: UNKNOWN
